idaes_examples/__init__.py
idaes_examples/browse.py
idaes_examples/build.py
idaes_examples/nbnew.py
idaes_examples/pytest.ini
idaes_examples/util.py
idaes_examples/archive/data_reconciliation/Boiler_scpc_PFD.svg
idaes_examples/archive/data_reconciliation/boiler_data_rec.py
idaes_examples/archive/data_reconciliation/boiler_flowsheet.png
idaes_examples/archive/data_reconciliation/boiler_flowsheet_recon_src.ipynb
idaes_examples/archive/data_reconciliation/boiler_plant_recon.csv
idaes_examples/archive/data_reconciliation/boiler_plant_recon_short.csv
idaes_examples/archive/data_reconciliation/boiler_scpc_init.svg
idaes_examples/archive/data_reconciliation/data_plot_book.pdf
idaes_examples/archive/data_reconciliation/econ.svg
idaes_examples/archive/data_reconciliation/econ_init.json.gz
idaes_examples/archive/data_reconciliation/econ_init.svg
idaes_examples/archive/data_reconciliation/econ_parmest_src.ipynb
idaes_examples/archive/data_reconciliation/econ_recon.csv
idaes_examples/archive/data_reconciliation/econ_recon_src.ipynb
idaes_examples/archive/data_reconciliation/index.md
idaes_examples/archive/data_reconciliation/optimal_run.json.gz
idaes_examples/archive/data_reconciliation/plant_data.csv
idaes_examples/archive/data_reconciliation/plant_data_meta.csv
idaes_examples/archive/dmf/data_management_framework.ipynb
idaes_examples/archive/dmf/data_management_framework_src.ipynb
idaes_examples/archive/dmf/index.md
idaes_examples/archive/dmf/my_workspace/resourcedb.json
idaes_examples/archive/dmf/my_workspace/files/928385c3acda4a449412c5bfbbaa83b5/data_management_framework.ipynb
idaes_examples/archive/matopt/bifunctional_surface_design.py
idaes_examples/archive/matopt/bifunctional_surface_design_src.ipynb
idaes_examples/archive/matopt/bimetallic_nanocluster_design.py
idaes_examples/archive/matopt/bimetallic_nanocluster_design_src.ipynb
idaes_examples/archive/matopt/canvas.cfg
idaes_examples/archive/matopt/canvas.pdb
idaes_examples/archive/matopt/canvas_sites.pdb
idaes_examples-2.9.0.dist-info/licenses/LICENSE.md
idaes_examples-2.9.0.dist-info/METADATA
idaes_examples-2.9.0.dist-info/WHEEL
idaes_examples-2.9.0.dist-info/entry_points.txt
idaes_examples-2.9.0.dist-info/top_level.txt
idaes_examples-2.9.0.dist-info/RECORD
