Metadata-Version: 2.4
Name: idaes-examples
Version: 2.9.0
Summary: IDAES Process Systems Engineering Examples
Author: The IDAES Project
Author-email: Dan Gunter <dkgunter@lbl.gov>
License: BSD
Project-URL: github, https://github.com/idaes/examples
Project-URL: issues, https://github.com/idaes/examples/issues
Keywords: IDAES,energy systems,chemical engineering,process modeling
Classifier: Development Status :: 3 - Alpha
Classifier: Intended Audience :: End Users/Desktop
Classifier: Intended Audience :: Science/Research
Classifier: License :: OSI Approved :: BSD License
Classifier: Natural Language :: English
Classifier: Operating System :: MacOS
Classifier: Operating System :: Microsoft :: Windows
Classifier: Operating System :: Unix
Classifier: Programming Language :: Python
Classifier: Programming Language :: Python :: 3
Classifier: Programming Language :: Python :: 3.9
Classifier: Programming Language :: Python :: 3.10
Classifier: Programming Language :: Python :: 3.11
Classifier: Programming Language :: Python :: 3.12
Classifier: Programming Language :: Python :: Implementation :: CPython
Classifier: Topic :: Scientific/Engineering :: Mathematics
Classifier: Topic :: Scientific/Engineering :: Chemistry
Classifier: Topic :: Software Development :: Libraries :: Python Modules
Requires-Python: >=3.9
License-File: LICENSE.md
Requires-Dist: setuptools
Requires-Dist: pyomo>=6.5.0
Requires-Dist: jupyter
Requires-Dist: importlib_resources
Provides-Extra: omlt
Requires-Dist: omlt; extra == "omlt"
Requires-Dist: tensorflow>=2.16.1; extra == "omlt"
Provides-Extra: idaes
Requires-Dist: idaes-pse; extra == "idaes"
Provides-Extra: testing
Requires-Dist: pytest-xdist~=3.0.2; extra == "testing"
Requires-Dist: pytest-reportlog~=0.1.2; extra == "testing"
Requires-Dist: nbclient; extra == "testing"
Requires-Dist: nbmake==1.5.*; extra == "testing"
Provides-Extra: docs
Requires-Dist: jupyter-book~=0.15.0; extra == "docs"
Requires-Dist: jupyter-cache; extra == "docs"
Requires-Dist: nbclient; extra == "docs"
Requires-Dist: nbformat; extra == "docs"
Provides-Extra: dev
Requires-Dist: idaes-examples[docs,testing]; extra == "dev"
Requires-Dist: black[jupyter]==24.3.0; extra == "dev"
Requires-Dist: addheader>=0.3.0; extra == "dev"
Requires-Dist: blessed~=1.20.0; extra == "dev"
Provides-Extra: packaging
Requires-Dist: build; extra == "packaging"
Requires-Dist: twine; extra == "packaging"
Dynamic: license-file
